essential_generators/__init__.py
essential_generators/document_generator.py
essential_generators/markov_textgen.json
essential_generators/markov_textgen.py
essential_generators/markov_wordgen.json
essential_generators/markov_wordgen.py
essential_generators/random_36.py
essential_generators/statistic_wordgen.py
essential_generators-1.0.dist-info/METADATA
essential_generators-1.0.dist-info/WHEEL
essential_generators-1.0.dist-info/top_level.txt
essential_generators-1.0.dist-info/RECORD
