Metadata-Version: 1.1
Name: essential_generators
Version: 1.0
Summary: Generate fake data for application testing based on simple but flexible templates.
Home-page: https://github.com/shane-mason/essential-document-generator
Author: scmason
Author-email: shane.c.mason@gmail.com
License: MIT
Platform: UNKNOWN
Classifier: Development Status :: 4 - Beta
Classifier: Intended Audience :: Developers
Classifier: Topic :: Software Development :: Build Tools
Classifier: License :: OSI Approved :: MIT License
Classifier: Programming Language :: Python :: 3
Classifier: Programming Language :: Python :: 3.3
Classifier: Programming Language :: Python :: 3.4
Classifier: Programming Language :: Python :: 3.5
